<annotation>
	<folder>voc2012</folder>
	<filename>2012_000776.jpg</filename>
	<rawname>5071-1-237.jpg</rawname>
	<source>
		<annotation>PASCAL VOC2012</annotation>
		<database>L</database>
		<image>L</image>
	</source>
	<size>
		<width>2048</width>
		<height>1489</height>
		<depth>3</depth>
	</size>
		<segmented>0</segmented>
	<object>
		<name>L</name>
		<pose>Unspecified</pose>
		<difficult>0</difficult>
		<bndbox>
			<xmin>1473</xmin>
			<ymin>1017</ymin>
			<xmax>1487</xmax>
			<ymax>1031</ymax>
		</bndbox>
		<point>
			<x>1480</x>
			<y>1024</y>
		</point>
	</object>
</annotation>