<annotation>
	<folder>voc2012</folder>
	<filename>2012_000824.jpg</filename>
	<rawname>3818-5-143.jpg</rawname>
	<source>
		<annotation>PASCAL VOC2012</annotation>
		<database>L</database>
		<image>L</image>
	</source>
	<size>
		<width>2048</width>
		<height>1489</height>
		<depth>3</depth>
	</size>
		<segmented>0</segmented>
	<object>
		<name>L</name>
		<pose>Unspecified</pose>
		<difficult>0</difficult>
		<bndbox>
			<xmin>679</xmin>
			<ymin>789</ymin>
			<xmax>693</xmax>
			<ymax>803</ymax>
		</bndbox>
		<point>
			<x>686</x>
			<y>796</y>
		</point>
	</object>
</annotation>